{"nm":"otoicon","ddd":0,"h":1000,"w":1000,"meta":{"g":"@lottiefiles/toolkit-js 0.33.2"},"layers":[{"ty":4,"nm":"Shape Layer 5","sr":1,"st":47.0000019143492,"op":60.0000024438501,"ip":47.0000019143492,"hd":false,"ddd":0,"bm":0,"hasMask":false,"ao":0,"ks":{"a":{"a":0,"k":[0,0,0],"ix":1},"s":{"a":0,"k":[100,100,100],"ix":6},"sk":{"a":0,"k":0},"p":{"a":0,"k":[468,500,0],"ix":2},"r":{"a":0,"k":0,"ix":10},"sa":{"a":0,"k":0},"o":{"a":0,"k":100,"ix":11}},"ef":[],"shapes":[{"ty":"gr","bm":0,"hd":false,"mn":"ADBE Vector Group","nm":"Shape 1","ix":1,"cix":2,"np":3,"it":[{"ty":"sh","bm":0,"hd":false,"mn":"ADBE Vector Shape - Group","nm":"Path 1","ix":1,"d":1,"ks":{"a":0,"k":{"c":false,"i":[[0,0],[0,0]],"o":[[0,0],[0,0]],"v":[[456,208],[-280,208]]},"ix":2}},{"ty":"st","bm":0,"hd":false,"mn":"ADBE Vector Graphic - Stroke","nm":"Stroke 1","lc":1,"lj":1,"ml":4,"o":{"a":0,"k":100,"ix":4},"w":{"a":0,"k":6,"ix":5},"c":{"a":0,"k":[0.2627,0.2667,0.2667],"ix":3}},{"ty":"fl","bm":0,"hd":false,"mn":"ADBE Vector Graphic - Fill","nm":"Fill 1","c":{"a":0,"k":[0.0588,0.9882,0.9373],"ix":4},"r":1,"o":{"a":0,"k":100,"ix":5}},{"ty":"tr","a":{"a":0,"k":[0,0],"ix":1},"s":{"a":0,"k":[100,100],"ix":3},"sk":{"a":0,"k":0,"ix":4},"p":{"a":0,"k":[0,0],"ix":2},"r":{"a":0,"k":0,"ix":6},"sa":{"a":0,"k":0,"ix":5},"o":{"a":0,"k":100,"ix":7}}]},{"ty":"tm","bm":0,"hd":false,"mn":"ADBE Vector Filter - Trim","nm":"Trim Paths 1","ix":2,"e":{"a":1,"k":[{"o":{"x":0.167,"y":0.167},"i":{"x":0.833,"y":0.833},"s":[0],"t":47},{"s":[100],"t":54.0000021994651}],"ix":2},"o":{"a":0,"k":0,"ix":3},"s":{"a":1,"k":[{"o":{"x":0.167,"y":0.167},"i":{"x":0.833,"y":0.833},"s":[0],"t":51},{"s":[100],"t":58.0000023623884}],"ix":1},"m":1}],"ind":1},{"ty":4,"nm":"Shape Layer 4","sr":1,"st":35.0000014255792,"op":48.0000019550801,"ip":35.0000014255792,"hd":false,"ddd":0,"bm":0,"hasMask":false,"ao":0,"ks":{"a":{"a":0,"k":[0,0,0],"ix":1},"s":{"a":0,"k":[100,100,100],"ix":6},"sk":{"a":0,"k":0},"p":{"a":0,"k":[468,500,0],"ix":2},"r":{"a":0,"k":0,"ix":10},"sa":{"a":0,"k":0},"o":{"a":0,"k":100,"ix":11}},"ef":[],"shapes":[{"ty":"gr","bm":0,"hd":false,"mn":"ADBE Vector Group","nm":"Shape 1","ix":1,"cix":2,"np":3,"it":[{"ty":"sh","bm":0,"hd":false,"mn":"ADBE Vector Shape - Group","nm":"Path 1","ix":1,"d":1,"ks":{"a":0,"k":{"c":false,"i":[[0,0],[0,0]],"o":[[0,0],[0,0]],"v":[[456,208],[-280,208]]},"ix":2}},{"ty":"st","bm":0,"hd":false,"mn":"ADBE Vector Graphic - Stroke","nm":"Stroke 1","lc":1,"lj":1,"ml":4,"o":{"a":0,"k":100,"ix":4},"w":{"a":0,"k":6,"ix":5},"c":{"a":0,"k":[0.2627,0.2667,0.2667],"ix":3}},{"ty":"fl","bm":0,"hd":false,"mn":"ADBE Vector Graphic - Fill","nm":"Fill 1","c":{"a":0,"k":[0.0588,0.9882,0.9373],"ix":4},"r":1,"o":{"a":0,"k":100,"ix":5}},{"ty":"tr","a":{"a":0,"k":[0,0],"ix":1},"s":{"a":0,"k":[100,100],"ix":3},"sk":{"a":0,"k":0,"ix":4},"p":{"a":0,"k":[0,0],"ix":2},"r":{"a":0,"k":0,"ix":6},"sa":{"a":0,"k":0,"ix":5},"o":{"a":0,"k":100,"ix":7}}]},{"ty":"tm","bm":0,"hd":false,"mn":"ADBE Vector Filter - Trim","nm":"Trim Paths 1","ix":2,"e":{"a":1,"k":[{"o":{"x":0.167,"y":0.167},"i":{"x":0.833,"y":0.833},"s":[0],"t":35},{"s":[100],"t":42.0000017106951}],"ix":2},"o":{"a":0,"k":0,"ix":3},"s":{"a":1,"k":[{"o":{"x":0.167,"y":0.167},"i":{"x":0.833,"y":0.833},"s":[0],"t":39},{"s":[100],"t":46.0000018736184}],"ix":1},"m":1}],"ind":2},{"ty":4,"nm":"Shape Layer 3","sr":1,"st":23.0000009368092,"op":36.0000014663101,"ip":23.0000009368092,"hd":false,"ddd":0,"bm":0,"hasMask":false,"ao":0,"ks":{"a":{"a":0,"k":[0,0,0],"ix":1},"s":{"a":0,"k":[100,100,100],"ix":6},"sk":{"a":0,"k":0},"p":{"a":0,"k":[468,500,0],"ix":2},"r":{"a":0,"k":0,"ix":10},"sa":{"a":0,"k":0},"o":{"a":0,"k":100,"ix":11}},"ef":[],"shapes":[{"ty":"gr","bm":0,"hd":false,"mn":"ADBE Vector Group","nm":"Shape 1","ix":1,"cix":2,"np":3,"it":[{"ty":"sh","bm":0,"hd":false,"mn":"ADBE Vector Shape - Group","nm":"Path 1","ix":1,"d":1,"ks":{"a":0,"k":{"c":false,"i":[[0,0],[0,0]],"o":[[0,0],[0,0]],"v":[[456,208],[-280,208]]},"ix":2}},{"ty":"st","bm":0,"hd":false,"mn":"ADBE Vector Graphic - Stroke","nm":"Stroke 1","lc":1,"lj":1,"ml":4,"o":{"a":0,"k":100,"ix":4},"w":{"a":0,"k":6,"ix":5},"c":{"a":0,"k":[0.2627,0.2667,0.2667],"ix":3}},{"ty":"fl","bm":0,"hd":false,"mn":"ADBE Vector Graphic - Fill","nm":"Fill 1","c":{"a":0,"k":[0.0588,0.9882,0.9373],"ix":4},"r":1,"o":{"a":0,"k":100,"ix":5}},{"ty":"tr","a":{"a":0,"k":[0,0],"ix":1},"s":{"a":0,"k":[100,100],"ix":3},"sk":{"a":0,"k":0,"ix":4},"p":{"a":0,"k":[0,0],"ix":2},"r":{"a":0,"k":0,"ix":6},"sa":{"a":0,"k":0,"ix":5},"o":{"a":0,"k":100,"ix":7}}]},{"ty":"tm","bm":0,"hd":false,"mn":"ADBE Vector Filter - Trim","nm":"Trim Paths 1","ix":2,"e":{"a":1,"k":[{"o":{"x":0.167,"y":0.167},"i":{"x":0.833,"y":0.833},"s":[0],"t":23},{"s":[100],"t":30.0000012219251}],"ix":2},"o":{"a":0,"k":0,"ix":3},"s":{"a":1,"k":[{"o":{"x":0.167,"y":0.167},"i":{"x":0.833,"y":0.833},"s":[0],"t":27},{"s":[100],"t":34.0000013848484}],"ix":1},"m":1}],"ind":3},{"ty":4,"nm":"Shape Layer 2","sr":1,"st":11.0000004480392,"op":24.00000097754,"ip":11.0000004480392,"hd":false,"ddd":0,"bm":0,"hasMask":false,"ao":0,"ks":{"a":{"a":0,"k":[0,0,0],"ix":1},"s":{"a":0,"k":[100,100,100],"ix":6},"sk":{"a":0,"k":0},"p":{"a":0,"k":[468,500,0],"ix":2},"r":{"a":0,"k":0,"ix":10},"sa":{"a":0,"k":0},"o":{"a":0,"k":100,"ix":11}},"ef":[],"shapes":[{"ty":"gr","bm":0,"hd":false,"mn":"ADBE Vector Group","nm":"Shape 1","ix":1,"cix":2,"np":3,"it":[{"ty":"sh","bm":0,"hd":false,"mn":"ADBE Vector Shape - Group","nm":"Path 1","ix":1,"d":1,"ks":{"a":0,"k":{"c":false,"i":[[0,0],[0,0]],"o":[[0,0],[0,0]],"v":[[456,208],[-280,208]]},"ix":2}},{"ty":"st","bm":0,"hd":false,"mn":"ADBE Vector Graphic - Stroke","nm":"Stroke 1","lc":1,"lj":1,"ml":4,"o":{"a":0,"k":100,"ix":4},"w":{"a":0,"k":6,"ix":5},"c":{"a":0,"k":[0.2627,0.2667,0.2667],"ix":3}},{"ty":"fl","bm":0,"hd":false,"mn":"ADBE Vector Graphic - Fill","nm":"Fill 1","c":{"a":0,"k":[0.0588,0.9882,0.9373],"ix":4},"r":1,"o":{"a":0,"k":100,"ix":5}},{"ty":"tr","a":{"a":0,"k":[0,0],"ix":1},"s":{"a":0,"k":[100,100],"ix":3},"sk":{"a":0,"k":0,"ix":4},"p":{"a":0,"k":[0,0],"ix":2},"r":{"a":0,"k":0,"ix":6},"sa":{"a":0,"k":0,"ix":5},"o":{"a":0,"k":100,"ix":7}}]},{"ty":"tm","bm":0,"hd":false,"mn":"ADBE Vector Filter - Trim","nm":"Trim Paths 1","ix":2,"e":{"a":1,"k":[{"o":{"x":0.167,"y":0.167},"i":{"x":0.833,"y":0.833},"s":[0],"t":11},{"s":[100],"t":18.000000733155}],"ix":2},"o":{"a":0,"k":0,"ix":3},"s":{"a":1,"k":[{"o":{"x":0.167,"y":0.167},"i":{"x":0.833,"y":0.833},"s":[0],"t":15},{"s":[100],"t":22.0000008960784}],"ix":1},"m":1}],"ind":4},{"ty":4,"nm":"Shape Layer 1","sr":1,"st":0,"op":13.0000005295009,"ip":0,"hd":false,"ddd":0,"bm":0,"hasMask":false,"ao":0,"ks":{"a":{"a":0,"k":[0,0,0],"ix":1},"s":{"a":0,"k":[100,100,100],"ix":6},"sk":{"a":0,"k":0},"p":{"a":0,"k":[468,500,0],"ix":2},"r":{"a":0,"k":0,"ix":10},"sa":{"a":0,"k":0},"o":{"a":0,"k":100,"ix":11}},"ef":[],"shapes":[{"ty":"gr","bm":0,"hd":false,"mn":"ADBE Vector Group","nm":"Shape 1","ix":1,"cix":2,"np":3,"it":[{"ty":"sh","bm":0,"hd":false,"mn":"ADBE Vector Shape - Group","nm":"Path 1","ix":1,"d":1,"ks":{"a":0,"k":{"c":false,"i":[[0,0],[0,0]],"o":[[0,0],[0,0]],"v":[[456,208],[-280,208]]},"ix":2}},{"ty":"st","bm":0,"hd":false,"mn":"ADBE Vector Graphic - Stroke","nm":"Stroke 1","lc":1,"lj":1,"ml":4,"o":{"a":0,"k":100,"ix":4},"w":{"a":0,"k":6,"ix":5},"c":{"a":0,"k":[0.2627,0.2667,0.2667],"ix":3}},{"ty":"fl","bm":0,"hd":false,"mn":"ADBE Vector Graphic - Fill","nm":"Fill 1","c":{"a":0,"k":[0.0588,0.9882,0.9373],"ix":4},"r":1,"o":{"a":0,"k":100,"ix":5}},{"ty":"tr","a":{"a":0,"k":[0,0],"ix":1},"s":{"a":0,"k":[100,100],"ix":3},"sk":{"a":0,"k":0,"ix":4},"p":{"a":0,"k":[0,0],"ix":2},"r":{"a":0,"k":0,"ix":6},"sa":{"a":0,"k":0,"ix":5},"o":{"a":0,"k":100,"ix":7}}]},{"ty":"tm","bm":0,"hd":false,"mn":"ADBE Vector Filter - Trim","nm":"Trim Paths 1","ix":2,"e":{"a":1,"k":[{"o":{"x":0.167,"y":0.167},"i":{"x":0.833,"y":0.833},"s":[0],"t":0},{"s":[100],"t":7.00000028511585}],"ix":2},"o":{"a":0,"k":0,"ix":3},"s":{"a":1,"k":[{"o":{"x":0.167,"y":0.167},"i":{"x":0.833,"y":0.833},"s":[0],"t":4},{"s":[100],"t":11.0000004480392}],"ix":1},"m":1}],"ind":5},{"ty":4,"nm":"Layer 2 Outlines","sr":1,"st":0,"op":301.000012259981,"ip":0,"hd":false,"ddd":0,"bm":0,"hasMask":false,"ao":0,"ks":{"a":{"a":0,"k":[189.045,269.881,0],"ix":1},"s":{"a":0,"k":[100,100,100],"ix":6},"sk":{"a":0,"k":0},"p":{"a":1,"k":[{"o":{"x":0.167,"y":0.167},"i":{"x":0.833,"y":0.833},"s":[190.657,193.44,0],"t":0,"ti":[0,0,0],"to":[0,-1.33333337306976,0]},{"o":{"x":0.167,"y":0.167},"i":{"x":0.833,"y":0.833},"s":[190.657,185.44,0],"t":7,"ti":[0,0,0],"to":[0,0,0]},{"o":{"x":0.167,"y":0.167},"i":{"x":0.833,"y":0.833},"s":[190.657,193.44,0],"t":14,"ti":[0,0,0],"to":[0,0,0]},{"o":{"x":0.167,"y":0.167},"i":{"x":0.833,"y":0.833},"s":[190.657,185.44,0],"t":21,"ti":[0,0,0],"to":[0,0,0]},{"o":{"x":0.167,"y":0.167},"i":{"x":0.833,"y":0.833},"s":[190.657,193.44,0],"t":28,"ti":[0,0,0],"to":[0,0,0]},{"o":{"x":0.167,"y":0.167},"i":{"x":0.833,"y":0.833},"s":[190.657,185.44,0],"t":36,"ti":[0,0,0],"to":[0,0,0]},{"o":{"x":0.167,"y":0.167},"i":{"x":0.833,"y":0.833},"s":[190.657,193.44,0],"t":44,"ti":[0,0,0],"to":[0,0,0]},{"o":{"x":0.167,"y":0.167},"i":{"x":0.833,"y":0.833},"s":[190.657,185.44,0],"t":52,"ti":[0,-1.33333337306976,0],"to":[0,0,0]},{"s":[190.657,193.44,0],"t":60.0000024438501}],"ix":2},"r":{"a":1,"k":[{"o":{"x":0.167,"y":0.167},"i":{"x":0.833,"y":0.833},"s":[0],"t":0},{"o":{"x":0.167,"y":0.167},"i":{"x":0.833,"y":0.833},"s":[1],"t":7},{"o":{"x":0.167,"y":0.167},"i":{"x":0.833,"y":0.833},"s":[0],"t":14},{"o":{"x":0.167,"y":0.167},"i":{"x":0.833,"y":0.833},"s":[1],"t":21},{"o":{"x":0.167,"y":0.167},"i":{"x":0.833,"y":0.833},"s":[0],"t":28},{"o":{"x":0.167,"y":0.167},"i":{"x":0.833,"y":0.833},"s":[1],"t":36},{"o":{"x":0.167,"y":0.167},"i":{"x":0.833,"y":0.833},"s":[0],"t":44},{"o":{"x":0.167,"y":0.167},"i":{"x":0.833,"y":0.833},"s":[1],"t":52},{"s":[0],"t":60.0000024438501}],"ix":10},"sa":{"a":0,"k":0},"o":{"a":0,"k":100,"ix":11}},"ef":[],"shapes":[{"ty":"gr","bm":0,"hd":false,"mn":"ADBE Vector Group","nm":"Shape 1","ix":1,"cix":2,"np":3,"it":[{"ty":"sh","bm":0,"hd":false,"mn":"ADBE Vector Shape - Group","nm":"Path 1","ix":1,"d":1,"ks":{"a":0,"k":{"c":false,"i":[[0,0]],"o":[[0,0]],"v":[[703.999,403.745]]},"ix":2}},{"ty":"st","bm":0,"hd":false,"mn":"ADBE Vector Graphic - Stroke","nm":"Stroke 1","lc":1,"lj":1,"ml":4,"o":{"a":0,"k":100,"ix":4},"w":{"a":0,"k":6,"ix":5},"c":{"a":0,"k":[0,0,0],"ix":3}},{"ty":"fl","bm":0,"hd":false,"mn":"ADBE Vector Graphic - Fill","nm":"Fill 1","c":{"a":0,"k":[0.0588,0.9882,0.9373],"ix":4},"r":1,"o":{"a":0,"k":100,"ix":5}},{"ty":"tr","a":{"a":0,"k":[0,0],"ix":1},"s":{"a":0,"k":[100,100],"ix":3},"sk":{"a":0,"k":0,"ix":4},"p":{"a":0,"k":[0,0],"ix":2},"r":{"a":0,"k":0,"ix":6},"sa":{"a":0,"k":0,"ix":5},"o":{"a":0,"k":100,"ix":7}}]},{"ty":"gr","bm":0,"hd":false,"mn":"ADBE Vector Group","nm":"Group 1","ix":2,"cix":2,"np":2,"it":[{"ty":"sh","bm":0,"hd":false,"mn":"ADBE Vector Shape - Group","nm":"Path 1","ix":1,"d":1,"ks":{"a":0,"k":{"c":true,"i":[[6.243,0],[2.436,-2.513],[0,0],[0,0],[0,0],[0,0],[0,0],[0,0],[-2.555,0],[0,-5.219],[0,0],[0,0],[0,0]],"o":[[-3.988,0],[0,0],[0,0],[0,0],[0,0],[0,0],[0,0],[2.44,-2.581],[3.218,0],[0,0],[0,0],[0,0],[0,-7.994]],"v":[[3.483,-9.672],[-5.855,-4.901],[-5.622,-11.026],[-5.622,-22.758],[-12.461,-22.758],[-12.461,22.758],[-5.622,22.758],[-5.622,0.648],[1.039,-3.286],[5.622,3.87],[5.622,22.758],[12.461,22.758],[12.461,2.898]]},"ix":2}},{"ty":"fl","bm":0,"hd":false,"mn":"ADBE Vector Graphic - Fill","nm":"Fill 1","c":{"a":0,"k":[0.0275,0.2941,0.4078],"ix":4},"r":1,"o":{"a":0,"k":100,"ix":5}},{"ty":"tr","a":{"a":0,"k":[0,0],"ix":1},"s":{"a":0,"k":[100,100],"ix":3},"sk":{"a":0,"k":0,"ix":4},"p":{"a":0,"k":[149.868,147.344],"ix":2},"r":{"a":0,"k":0,"ix":6},"sa":{"a":0,"k":0,"ix":5},"o":{"a":0,"k":100,"ix":7}}]},{"ty":"gr","bm":0,"hd":false,"mn":"ADBE Vector Group","nm":"Group 2","ix":3,"cix":2,"np":4,"it":[{"ty":"sh","bm":0,"hd":false,"mn":"ADBE Vector Shape - Group","nm":"Path 1","ix":1,"d":1,"ks":{"a":0,"k":{"c":true,"i":[[0,-2.969],[0,0],[0,0],[0,0],[-1.282,2.648],[0,0]],"o":[[0,0],[0,0],[0,0],[1.446,-2.732],[0,0],[-0.157,2.969]],"v":[[3.732,-6.344],[3.732,5.22],[-9.679,5.22],[-0.361,-8.991],[3.813,-16.943],[4.134,-16.943]]},"ix":2}},{"ty":"sh","bm":0,"hd":false,"mn":"ADBE Vector Shape - Group","nm":"Path 2","ix":2,"d":1,"ks":{"a":0,"k":{"c":true,"i":[[0,0],[0,0],[0,0],[0,0],[0,0],[0,0],[0,0],[0,0],[0,0],[0,0],[0,0]],"o":[[0,0],[0,0],[0,0],[0,0],[0,0],[0,0],[0,0],[0,0],[0,0],[0,0],[0,0]],"v":[[12.407,-25.536],[1.406,-25.536],[-18.831,6.108],[-18.831,12.367],[3.732,12.367],[3.732,25.536],[12.407,25.536],[12.407,12.367],[18.831,12.367],[18.831,5.22],[12.407,5.22]]},"ix":2}},{"ty":"mm","bm":0,"hd":false,"mn":"ADBE Vector Filter - Merge","nm":"Merge Paths 1","mm":1},{"ty":"fl","bm":0,"hd":false,"mn":"ADBE Vector Graphic - Fill","nm":"Fill 1","c":{"a":0,"k":[0.0275,0.2941,0.4078],"ix":4},"r":1,"o":{"a":0,"k":100,"ix":5}},{"ty":"tr","a":{"a":0,"k":[0,0],"ix":1},"s":{"a":0,"k":[100,100],"ix":3},"sk":{"a":0,"k":0,"ix":4},"p":{"a":0,"k":[116.896,144.752],"ix":2},"r":{"a":0,"k":0,"ix":6},"sa":{"a":0,"k":0,"ix":5},"o":{"a":0,"k":100,"ix":7}}]},{"ty":"gr","bm":0,"hd":false,"mn":"ADBE Vector Group","nm":"Group 3","ix":4,"cix":2,"np":2,"it":[{"ty":"sh","bm":0,"hd":false,"mn":"ADBE Vector Shape - Group","nm":"Path 1","ix":1,"d":1,"ks":{"a":0,"k":{"c":true,"i":[[2.651,-0.237],[0,9.068],[9.798,0],[4.661,-4.982],[0,0],[-3.934,0],[0,-5.388],[14.214,-13.728],[0,0],[0,0],[0,0],[0,0]],"o":[[10.12,-10.675],[0,-9.482],[-6.988,0],[0,0],[2.728,-3.054],[5.46,0],[0,7.79],[0,0],[0,0],[0,0],[0,0],[-2.492,0]],"v":[[-3.575,18.71],[14.978,-10.354],[-1.164,-26.018],[-17.469,-18.143],[-12.326,-13.01],[-2.37,-18.711],[6.063,-9.872],[-17.067,20.638],[-17.067,26.018],[17.469,26.018],[17.469,18.151],[4.939,18.151]]},"ix":2}},{"ty":"fl","bm":0,"hd":false,"mn":"ADBE Vector Graphic - Fill","nm":"Fill 1","c":{"a":0,"k":[0.0275,0.2941,0.4078],"ix":4},"r":1,"o":{"a":0,"k":100,"ix":5}},{"ty":"tr","a":{"a":0,"k":[0,0],"ix":1},"s":{"a":0,"k":[100,100],"ix":3},"sk":{"a":0,"k":0,"ix":4},"p":{"a":0,"k":[75.541,144.27],"ix":2},"r":{"a":0,"k":0,"ix":6},"sa":{"a":0,"k":0,"ix":5},"o":{"a":0,"k":100,"ix":7}}]},{"ty":"gr","bm":0,"hd":false,"mn":"ADBE Vector Group","nm":"Group 4","ix":5,"cix":2,"np":2,"it":[{"ty":"sh","bm":0,"hd":false,"mn":"ADBE Vector Shape - Group","nm":"Path 1","ix":1,"d":1,"ks":{"a":0,"k":{"c":true,"i":[[17.997,0],[3.646,0.692],[8.162,11.488],[-2.948,13.458],[-19.234,5.355],[0,0],[-1.873,-2.648],[-1.328,-0.423],[-0.427,-0.05],[-1.363,1.007],[0,0],[0.16,1.962],[1.844,0.982],[0,0],[0.732,0.085],[1.358,-1.869],[-2.677,-1.489],[0,0],[5.413,-24.742],[-10.163,-14.295],[-17.996,-3.409],[-4.584,0],[-11.808,20.994],[0,0]],"o":[[-3.696,0],[-14.468,-2.74],[-8.167,-11.487],[4.115,-18.829],[0,0],[-2.669,1.97],[0.787,1.108],[0.411,0.126],[1.722,0.212],[0,0],[1.662,-1.234],[-0.161,-1.971],[0,0],[-0.625,-0.33],[-2.313,-0.262],[-1.861,2.572],[0,0],[-25.897,5.71],[-3.663,16.748],[10.159,14.295],[4.525,0.854],[25.507,0],[0,0],[-10.396,13.702]],"v":[[5.102,58.563],[-5.957,57.523],[-41.052,35.463],[-49.147,-3.219],[-10.711,-42.214],[-19.702,-35.589],[-21.492,-27.368],[-18.231,-25.016],[-16.979,-24.747],[-12.195,-25.982],[14.386,-45.581],[16.78,-50.68],[13.582,-55.393],[-13.659,-70.245],[-15.706,-70.88],[-21.741,-68.24],[-20.286,-60.865],[-10.863,-55.23],[-62.393,-5.73],[-52.319,42.4],[-8.655,69.848],[5.077,71.141],[66.056,36.698],[50.344,36.698]]},"ix":2}},{"ty":"fl","bm":0,"hd":false,"mn":"ADBE Vector Graphic - Fill","nm":"Fill 1","c":{"a":0,"k":[0.2314,0.5098,0.9647],"ix":4},"r":1,"o":{"a":0,"k":100,"ix":5}},{"ty":"tr","a":{"a":0,"k":[0,0],"ix":1},"s":{"a":0,"k":[100,100],"ix":3},"sk":{"a":0,"k":0,"ix":4},"p":{"a":0,"k":[92.527,139.529],"ix":2},"r":{"a":0,"k":0,"ix":6},"sa":{"a":0,"k":0,"ix":5},"o":{"a":0,"k":100,"ix":7}}]},{"ty":"gr","bm":0,"hd":false,"mn":"ADBE Vector Group","nm":"Group 5","ix":6,"cix":2,"np":2,"it":[{"ty":"sh","bm":0,"hd":false,"mn":"ADBE Vector Shape - Group","nm":"Path 1","ix":1,"d":1,"ks":{"a":0,"k":{"c":true,"i":[[0,-41.278],[0,0],[0,0],[0,0],[0,0]],"o":[[0,0],[0,0],[0,0],[0,0],[-41.282,0]],"v":[[-94.396,-77.862],[-94.396,137.631],[94.396,137.631],[94.396,-137.631],[-19.648,-137.631]]},"ix":2}},{"ty":"fl","bm":0,"hd":false,"mn":"ADBE Vector Graphic - Fill","nm":"Fill 1","c":{"a":0,"k":[0.3804,0.5686,0.8667],"ix":4},"r":1,"o":{"a":0,"k":100,"ix":5}},{"ty":"tr","a":{"a":0,"k":[0,0],"ix":1},"s":{"a":0,"k":[100,100],"ix":3},"sk":{"a":0,"k":0,"ix":4},"p":{"a":0,"k":[94.646,137.881],"ix":2},"r":{"a":0,"k":0,"ix":6},"sa":{"a":0,"k":0,"ix":5},"o":{"a":0,"k":100,"ix":7}}]},{"ty":"gr","bm":0,"hd":false,"mn":"ADBE Vector Group","nm":"Group 6","ix":7,"cix":2,"np":2,"it":[{"ty":"sh","bm":0,"hd":false,"mn":"ADBE Vector Shape - Group","nm":"Path 1","ix":1,"d":1,"ks":{"a":0,"k":{"c":true,"i":[[41.283,0],[0,0],[0,0],[0,0],[0,0]],"o":[[0,0],[0,0],[0,0],[0,0],[0,-41.278]],"v":[[19.645,-137.631],[-94.399,-137.631],[-94.399,137.631],[94.399,137.631],[94.399,-77.862]]},"ix":2}},{"ty":"fl","bm":0,"hd":false,"mn":"ADBE Vector Graphic - Fill","nm":"Fill 1","c":{"a":0,"k":[0.2314,0.5098,0.9647],"ix":4},"r":1,"o":{"a":0,"k":100,"ix":5}},{"ty":"tr","a":{"a":0,"k":[0,0],"ix":1},"s":{"a":0,"k":[100,100],"ix":3},"sk":{"a":0,"k":0,"ix":4},"p":{"a":0,"k":[283.442,137.881],"ix":2},"r":{"a":0,"k":0,"ix":6},"sa":{"a":0,"k":0,"ix":5},"o":{"a":0,"k":100,"ix":7}}]}],"ind":6,"parent":8},{"ty":4,"nm":"Layer 3 Outlines","sr":1,"st":0,"op":301.000012259981,"ip":0,"hd":false,"ddd":0,"bm":0,"hasMask":false,"ao":0,"ks":{"a":{"a":0,"k":[47.959,47.956,0],"ix":1},"s":{"a":0,"k":[100,100,100],"ix":6},"sk":{"a":0,"k":0},"p":{"a":0,"k":[334.75,661.874,0],"ix":2},"r":{"a":1,"k":[{"o":{"x":0.167,"y":0.167},"i":{"x":0.833,"y":0.833},"s":[0],"t":0},{"s":[3600],"t":60.0000024438501}],"ix":10},"sa":{"a":0,"k":0},"o":{"a":0,"k":100,"ix":11}},"ef":[],"shapes":[{"ty":"gr","bm":0,"hd":false,"mn":"ADBE Vector Group","nm":"Group 1","ix":1,"cix":2,"np":2,"it":[{"ty":"sh","bm":0,"hd":false,"mn":"ADBE Vector Shape - Group","nm":"Path 1","ix":1,"d":1,"ks":{"a":0,"k":{"c":true,"i":[[16.58,0],[5.367,-5.431],[0,0],[0,8.29]],"o":[[-8.289,0],[0,0],[5.486,-5.422],[0,-16.638]],"v":[[-4.413,-25.643],[-25.645,-16.811],[16.818,25.643],[25.645,4.42]]},"ix":2}},{"ty":"fl","bm":0,"hd":false,"mn":"ADBE Vector Graphic - Fill","nm":"Fill 1","c":{"a":0,"k":[0.2314,0.5098,0.9647],"ix":4},"r":1,"o":{"a":0,"k":100,"ix":5}},{"ty":"tr","a":{"a":0,"k":[0,0],"ix":1},"s":{"a":0,"k":[100,100],"ix":3},"sk":{"a":0,"k":0,"ix":4},"p":{"a":0,"k":[52.37,43.562],"ix":2},"r":{"a":0,"k":0,"ix":6},"sa":{"a":0,"k":0,"ix":5},"o":{"a":0,"k":100,"ix":7}}]},{"ty":"gr","bm":0,"hd":false,"mn":"ADBE Vector Group","nm":"Group 2","ix":2,"cix":2,"np":2,"it":[{"ty":"sh","bm":0,"hd":false,"mn":"ADBE Vector Shape - Group","nm":"Path 1","ix":1,"d":1,"ks":{"a":0,"k":{"c":true,"i":[[0,-8.289],[-16.579,0],[-5.426,5.43],[0,0]],"o":[[0,16.58],[8.289,0],[0,0],[-5.485,5.481]],"v":[[-25.645,-4.413],[4.413,25.643],[25.645,16.812],[-16.819,-25.643]]},"ix":2}},{"ty":"fl","bm":0,"hd":false,"mn":"ADBE Vector Graphic - Fill","nm":"Fill 1","c":{"a":0,"k":[0.3804,0.5686,0.8667],"ix":4},"r":1,"o":{"a":0,"k":100,"ix":5}},{"ty":"tr","a":{"a":0,"k":[0,0],"ix":1},"s":{"a":0,"k":[100,100],"ix":3},"sk":{"a":0,"k":0,"ix":4},"p":{"a":0,"k":[43.543,52.394],"ix":2},"r":{"a":0,"k":0,"ix":6},"sa":{"a":0,"k":0,"ix":5},"o":{"a":0,"k":100,"ix":7}}]},{"ty":"gr","bm":0,"hd":false,"mn":"ADBE Vector Group","nm":"Group 3","ix":3,"cix":2,"np":4,"it":[{"ty":"sh","bm":0,"hd":false,"mn":"ADBE Vector Shape - Group","nm":"Path 1","ix":1,"d":1,"ks":{"a":0,"k":{"c":true,"i":[[5.486,-5.422],[8.289,0],[0,16.58],[-5.485,5.481],[-8.29,0],[0,-16.637]],"o":[[-5.426,5.431],[-16.58,0],[0,-8.289],[5.368,-5.431],[16.579,0],[0,8.29]],"v":[[21.229,21.248],[-0.002,30.08],[-30.06,0.024],[-21.234,-21.205],[-0.002,-30.036],[30.056,0.024]]},"ix":2}},{"ty":"sh","bm":0,"hd":false,"mn":"ADBE Vector Shape - Group","nm":"Path 2","ix":2,"d":1,"ks":{"a":0,"k":{"c":true,"i":[[1.467,2.698],[3.236,3.239],[13.174,0],[8.631,-8.637],[2.204,-4.06],[0.931,-2.985],[0,-4.94],[-26.349,0],[0,26.349],[1.395,4.484]],"o":[[-2.204,-4.06],[-8.637,-8.637],[-13.175,0],[-3.236,3.239],[-1.467,2.698],[-1.396,4.484],[0,26.349],[26.349,0],[0,-4.94],[-0.927,-2.985]],"v":[[41.949,-22.736],[33.735,-33.732],[-0.002,-47.706],[-33.735,-33.732],[-41.954,-22.736],[-45.565,-14.186],[-47.709,0.001],[-0.002,47.706],[47.709,0.001],[45.561,-14.186]]},"ix":2}},{"ty":"mm","bm":0,"hd":false,"mn":"ADBE Vector Filter - Merge","nm":"Merge Paths 1","mm":1},{"ty":"fl","bm":0,"hd":false,"mn":"ADBE Vector Graphic - Fill","nm":"Fill 1","c":{"a":0,"k":[0.2627,0.2667,0.2667],"ix":4},"r":1,"o":{"a":0,"k":100,"ix":5}},{"ty":"tr","a":{"a":0,"k":[0,0],"ix":1},"s":{"a":0,"k":[100,100],"ix":3},"sk":{"a":0,"k":0,"ix":4},"p":{"a":0,"k":[47.959,47.956],"ix":2},"r":{"a":0,"k":0,"ix":6},"sa":{"a":0,"k":0,"ix":5},"o":{"a":0,"k":100,"ix":7}}]}],"ind":7},{"ty":4,"nm":"Layer 4 Outlines","sr":1,"st":0,"op":301.000012259981,"ip":0,"hd":false,"ddd":0,"bm":0,"hasMask":false,"ao":0,"ks":{"a":{"a":0,"k":[307.842,240.253,0],"ix":1},"s":{"a":0,"k":[100,100,100],"ix":6},"sk":{"a":0,"k":0},"p":{"a":1,"k":[{"o":{"x":0.167,"y":0.167},"i":{"x":0.833,"y":0.833},"s":[496.567,623.951,0],"t":0,"ti":[0,0,0],"to":[0,0,0]},{"o":{"x":0.167,"y":0.167},"i":{"x":0.833,"y":0.833},"s":[496.567,615.951,0],"t":7,"ti":[0,0,0],"to":[0,0,0]},{"o":{"x":0.167,"y":0.167},"i":{"x":0.833,"y":0.833},"s":[496.567,623.951,0],"t":14,"ti":[0,0,0],"to":[0,0,0]},{"o":{"x":0.167,"y":0.167},"i":{"x":0.833,"y":0.833},"s":[496.567,615.951,0],"t":21,"ti":[0,0,0],"to":[0,0,0]},{"o":{"x":0.167,"y":0.167},"i":{"x":0.833,"y":0.833},"s":[496.567,623.951,0],"t":28,"ti":[0,0,0],"to":[0,0,0]},{"o":{"x":0.167,"y":0.167},"i":{"x":0.833,"y":0.833},"s":[496.567,615.951,0],"t":36,"ti":[0,0,0],"to":[0,0,0]},{"o":{"x":0.167,"y":0.167},"i":{"x":0.833,"y":0.833},"s":[496.567,623.951,0],"t":44,"ti":[0,0,0],"to":[0,0,0]},{"o":{"x":0.167,"y":0.167},"i":{"x":0.833,"y":0.833},"s":[496.567,615.951,0],"t":52,"ti":[0,0,0],"to":[0,0,0]},{"s":[496.567,623.951,0],"t":60.0000024438501}],"ix":2},"r":{"a":0,"k":0,"ix":10},"sa":{"a":0,"k":0},"o":{"a":0,"k":100,"ix":11}},"ef":[],"shapes":[{"ty":"gr","bm":0,"hd":false,"mn":"ADBE Vector Group","nm":"Group 1","ix":1,"cix":2,"np":2,"it":[{"ty":"sh","bm":0,"hd":false,"mn":"ADBE Vector Shape - Group","nm":"Path 1","ix":1,"d":1,"ks":{"a":0,"k":{"c":true,"i":[[-3.967,-6.455],[0,0],[0,0],[0,0]],"o":[[0,0],[0,0],[0,0],[6.142,4.407]],"v":[[-29.637,8.235],[44.968,8.235],[44.968,-8.235],[-44.968,-8.235]]},"ix":2}},{"ty":"fl","bm":0,"hd":false,"mn":"ADBE Vector Graphic - Fill","nm":"Fill 1","c":{"a":0,"k":[0.1098,0.6588,0.9412],"ix":4},"r":1,"o":{"a":0,"k":100,"ix":5}},{"ty":"tr","a":{"a":0,"k":[0,0],"ix":1},"s":{"a":0,"k":[100,100],"ix":3},"sk":{"a":0,"k":0,"ix":4},"p":{"a":0,"k":[551.761,239.897],"ix":2},"r":{"a":0,"k":0,"ix":6},"sa":{"a":0,"k":0,"ix":5},"o":{"a":0,"k":100,"ix":7}}]},{"ty":"gr","bm":0,"hd":false,"mn":"ADBE Vector Group","nm":"Group 2","ix":2,"cix":2,"np":2,"it":[{"ty":"sh","bm":0,"hd":false,"mn":"ADBE Vector Shape - Group","nm":"Path 1","ix":1,"d":1,"ks":{"a":0,"k":{"c":true,"i":[[0,0],[0,0],[0,0],[-12.498,0],[-9.431,-6.835],[0,0],[-12.523,0],[-9.426,-6.835],[0,0],[0,0],[0,0]],"o":[[0,0],[0,0],[9.432,-6.835],[12.498,0],[0,0],[9.427,-6.835],[12.527,0],[0,0],[0,0],[0,0],[0,0]],"v":[[-278.119,1.112],[-278.119,11.651],[-206.119,11.651],[-172.584,0.773],[-139.05,11.651],[121.118,11.651],[154.648,0.773],[188.182,11.651],[278.119,11.651],[278.119,-11.651],[-278.119,-11.651]]},"ix":2}},{"ty":"fl","bm":0,"hd":false,"mn":"ADBE Vector Graphic - Fill","nm":"Fill 1","c":{"a":0,"k":[0.2314,0.5098,0.9647],"ix":4},"r":1,"o":{"a":0,"k":100,"ix":5}},{"ty":"tr","a":{"a":0,"k":[0,0],"ix":1},"s":{"a":0,"k":[100,100],"ix":3},"sk":{"a":0,"k":0,"ix":4},"p":{"a":0,"k":[318.611,220.01],"ix":2},"r":{"a":0,"k":0,"ix":6},"sa":{"a":0,"k":0,"ix":5},"o":{"a":0,"k":100,"ix":7}}]},{"ty":"gr","bm":0,"hd":false,"mn":"ADBE Vector Group","nm":"Group 3","ix":3,"cix":2,"np":2,"it":[{"ty":"sh","bm":0,"hd":false,"mn":"ADBE Vector Shape - Group","nm":"Path 1","ix":1,"d":1,"ks":{"a":0,"k":{"c":true,"i":[[-0.893,-8.771],[0,0],[0,0],[0,0]],"o":[[0,0],[0,0],[0,0],[4.424,7.155]],"v":[[-29.085,12.061],[37.303,12.061],[37.303,-12.061],[-37.303,-12.061]]},"ix":2}},{"ty":"fl","bm":0,"hd":false,"mn":"ADBE Vector Graphic - Fill","nm":"Fill 1","c":{"a":0,"k":[0.2314,0.5098,0.9647],"ix":4},"r":1,"o":{"a":0,"k":100,"ix":5}},{"ty":"tr","a":{"a":0,"k":[0,0],"ix":1},"s":{"a":0,"k":[100,100],"ix":3},"sk":{"a":0,"k":0,"ix":4},"p":{"a":0,"k":[559.427,260.193],"ix":2},"r":{"a":0,"k":0,"ix":6},"sa":{"a":0,"k":0,"ix":5},"o":{"a":0,"k":100,"ix":7}}]},{"ty":"gr","bm":0,"hd":false,"mn":"ADBE Vector Group","nm":"Group 4","ix":4,"cix":2,"np":2,"it":[{"ty":"sh","bm":0,"hd":false,"mn":"ADBE Vector Shape - Group","nm":"Path 1","ix":1,"d":1,"ks":{"a":0,"k":{"c":true,"i":[[0,0],[0,0],[0,0],[0,0],[0,0],[0,0]],"o":[[0,0],[0,0],[0,0],[0,0],[0,0],[0,0]],"v":[[-20.121,18.021],[20.121,18.021],[20.121,8.988],[20.121,-7.482],[20.121,-18.021],[-20.121,-18.021]]},"ix":2}},{"ty":"fl","bm":0,"hd":false,"mn":"ADBE Vector Graphic - Fill","nm":"Fill 1","c":{"a":0,"k":[0.2627,0.2667,0.2667],"ix":4},"r":1,"o":{"a":0,"k":100,"ix":5}},{"ty":"tr","a":{"a":0,"k":[0,0],"ix":1},"s":{"a":0,"k":[100,100],"ix":3},"sk":{"a":0,"k":0,"ix":4},"p":{"a":0,"k":[20.371,239.144],"ix":2},"r":{"a":0,"k":0,"ix":6},"sa":{"a":0,"k":0,"ix":5},"o":{"a":0,"k":100,"ix":7}}]},{"ty":"gr","bm":0,"hd":false,"mn":"ADBE Vector Group","nm":"Group 5","ix":5,"cix":2,"np":2,"it":[{"ty":"sh","bm":0,"hd":false,"mn":"ADBE Vector Shape - Group","nm":"Path 1","ix":1,"d":1,"ks":{"a":0,"k":{"c":true,"i":[[0,0],[0,0],[0,0],[14.168,21.375]],"o":[[0,0],[0,0],[0,0],[0,0]],"v":[[-63.306,-21.375],[-63.306,21.375],[63.306,21.375],[40.726,-21.375]]},"ix":2}},{"ty":"fl","bm":0,"hd":false,"mn":"ADBE Vector Graphic - Fill","nm":"Fill 1","c":{"a":0,"k":[0.8824,0.9451,1],"ix":4},"r":1,"o":{"a":0,"k":100,"ix":5}},{"ty":"tr","a":{"a":0,"k":[0,0],"ix":1},"s":{"a":0,"k":[100,100],"ix":3},"sk":{"a":0,"k":0,"ix":4},"p":{"a":0,"k":[480.742,90.208],"ix":2},"r":{"a":0,"k":0,"ix":6},"sa":{"a":0,"k":0,"ix":5},"o":{"a":0,"k":100,"ix":7}}]},{"ty":"gr","bm":0,"hd":false,"mn":"ADBE Vector Group","nm":"Group 6","ix":6,"cix":2,"np":2,"it":[{"ty":"sh","bm":0,"hd":false,"mn":"ADBE Vector Shape - Group","nm":"Path 1","ix":1,"d":1,"ks":{"a":0,"k":{"c":true,"i":[[0,0],[0,0],[0,0],[0,0]],"o":[[0,0],[0,0],[0,0],[0,0]],"v":[[-20.466,5.642],[20.466,5.642],[20.466,-5.642],[-20.466,-5.642]]},"ix":2}},{"ty":"fl","bm":0,"hd":false,"mn":"ADBE Vector Graphic - Fill","nm":"Fill 1","c":{"a":0,"k":[0.2627,0.2667,0.2667],"ix":4},"r":1,"o":{"a":0,"k":100,"ix":5}},{"ty":"tr","a":{"a":0,"k":[0,0],"ix":1},"s":{"a":0,"k":[100,100],"ix":3},"sk":{"a":0,"k":0,"ix":4},"p":{"a":0,"k":[433.909,135.267],"ix":2},"r":{"a":0,"k":0,"ix":6},"sa":{"a":0,"k":0,"ix":5},"o":{"a":0,"k":100,"ix":7}}]},{"ty":"gr","bm":0,"hd":false,"mn":"ADBE Vector Group","nm":"Group 7","ix":7,"cix":2,"np":2,"it":[{"ty":"sh","bm":0,"hd":false,"mn":"ADBE Vector Shape - Group","nm":"Path 1","ix":1,"d":1,"ks":{"a":0,"k":{"c":true,"i":[[23.57,-0.752],[0,0],[0,0],[0,0]],"o":[[0,0],[0,0],[0,0],[-14.435,-21.73]],"v":[[-6.369,-20.983],[-52.017,-20.983],[-52.017,21.734],[52.017,21.734]]},"ix":2}},{"ty":"fl","bm":0,"hd":false,"mn":"ADBE Vector Graphic - Fill","nm":"Fill 1","c":{"a":0,"k":[0.8549,0.8863,0.9176],"ix":4},"r":1,"o":{"a":0,"k":100,"ix":5}},{"ty":"tr","a":{"a":0,"k":[0,0],"ix":1},"s":{"a":0,"k":[100,100],"ix":3},"sk":{"a":0,"k":0,"ix":4},"p":{"a":0,"k":[469.453,47.099],"ix":2},"r":{"a":0,"k":0,"ix":6},"sa":{"a":0,"k":0,"ix":5},"o":{"a":0,"k":100,"ix":7}}]},{"ty":"gr","bm":0,"hd":false,"mn":"ADBE Vector Group","nm":"Group 8","ix":8,"cix":2,"np":2,"it":[{"ty":"sh","bm":0,"hd":false,"mn":"ADBE Vector Shape - Group","nm":"Path 1","ix":1,"d":1,"ks":{"a":0,"k":{"c":true,"i":[[0,0],[0,0],[0,0],[0,0],[0,0],[0,0],[-0.377,1.709],[0,0.305],[0,0],[0,0],[0,0]],"o":[[0,0],[0,0],[0,0],[0,0],[0,0],[1.725,0],[0.064,-0.287],[0,0],[0,0],[0,0],[0,0]],"v":[[93.974,-20.923],[-98.119,-20.923],[-98.119,20.923],[94.236,20.923],[94.388,20.923],[94.478,20.923],[98.013,17.936],[98.119,17.048],[98.119,-17.091],[98.119,-19.603],[96.253,-20.923]]},"ix":2}},{"ty":"fl","bm":0,"hd":false,"mn":"ADBE Vector Graphic - Fill","nm":"Fill 1","c":{"a":0,"k":[0.1098,0.6588,0.9412],"ix":4},"r":1,"o":{"a":0,"k":100,"ix":5}},{"ty":"tr","a":{"a":0,"k":[0,0],"ix":1},"s":{"a":0,"k":[100,100],"ix":3},"sk":{"a":0,"k":0,"ix":4},"p":{"a":0,"k":[494.061,178.148],"ix":2},"r":{"a":0,"k":0,"ix":6},"sa":{"a":0,"k":0,"ix":5},"o":{"a":0,"k":100,"ix":7}}]},{"ty":"gr","bm":0,"hd":false,"mn":"ADBE Vector Group","nm":"Group 9","ix":9,"cix":2,"np":5,"it":[{"ty":"sh","bm":0,"hd":false,"mn":"ADBE Vector Shape - Group","nm":"Path 1","ix":1,"d":1,"ks":{"a":0,"k":{"c":true,"i":[[0,0],[0,0],[0,0],[0,0],[-14.434,-21.73],[0,0]],"o":[[0,0],[0,0],[0,0],[23.571,-0.752],[14.168,21.375],[0,0]],"v":[[-74.552,32.845],[-74.552,-9.905],[-74.552,-52.622],[-28.906,-52.622],[29.48,-9.905],[52.06,32.845]]},"ix":2}},{"ty":"sh","bm":0,"hd":false,"mn":"ADBE Vector Shape - Group","nm":"Path 2","ix":2,"d":1,"ks":{"a":0,"k":{"c":true,"i":[[0,0],[0,0],[0,0],[0,0]],"o":[[0,0],[0,0],[0,0],[0,0]],"v":[[-37.615,62.171],[-78.547,62.171],[-78.547,50.887],[-37.615,50.887]]},"ix":2}},{"ty":"sh","bm":0,"hd":false,"mn":"ADBE Vector Shape - Group","nm":"Path 3","ix":3,"d":1,"ks":{"a":0,"k":{"c":true,"i":[[57.498,0],[0,0],[0,0],[0,0],[0.626,1.573]],"o":[[0,0],[0,0],[0,0],[-0.428,-1.988],[-1.814,-4.551]],"v":[[-26.297,-78.488],[-96.047,-78.488],[-96.047,78.488],[96.047,78.488],[94.477,73.1]]},"ix":2}},{"ty":"mm","bm":0,"hd":false,"mn":"ADBE Vector Filter - Merge","nm":"Merge Paths 1","mm":1},{"ty":"fl","bm":0,"hd":false,"mn":"ADBE Vector Graphic - Fill","nm":"Fill 1","c":{"a":0,"k":[0.2314,0.5098,0.9647],"ix":4},"r":1,"o":{"a":0,"k":100,"ix":5}},{"ty":"tr","a":{"a":0,"k":[0,0],"ix":1},"s":{"a":0,"k":[100,100],"ix":3},"sk":{"a":0,"k":0,"ix":4},"p":{"a":0,"k":[491.988,78.738],"ix":2},"r":{"a":0,"k":0,"ix":6},"sa":{"a":0,"k":0,"ix":5},"o":{"a":0,"k":100,"ix":7}}]},{"ty":"gr","bm":0,"hd":false,"mn":"ADBE Vector Group","nm":"Group 10","ix":10,"cix":2,"np":2,"it":[{"ty":"sh","bm":0,"hd":false,"mn":"ADBE Vector Shape - Group","nm":"Path 1","ix":1,"d":1,"ks":{"a":0,"k":{"c":true,"i":[[3.493,0],[0,0],[0,0],[0.064,-0.287],[0,0],[0,3.493],[0,0]],"o":[[0,0],[0,0],[0,0.305],[0,0],[3.493,0],[0,0],[0,-3.493]],"v":[[-2.669,-17.514],[-3.574,-17.514],[-3.574,16.626],[-3.68,17.514],[-2.669,17.514],[3.68,11.163],[3.68,-11.169]]},"ix":2}},{"ty":"fl","bm":0,"hd":false,"mn":"ADBE Vector Graphic - Fill","nm":"Fill 1","c":{"a":0,"k":[0.2314,0.5098,0.9647],"ix":4},"r":1,"o":{"a":0,"k":100,"ix":5}},{"ty":"tr","a":{"a":0,"k":[0,0],"ix":1},"s":{"a":0,"k":[100,100],"ix":3},"sk":{"a":0,"k":0,"ix":4},"p":{"a":0,"k":[595.753,178.571],"ix":2},"r":{"a":0,"k":0,"ix":6},"sa":{"a":0,"k":0,"ix":5},"o":{"a":0,"k":100,"ix":7}}]},{"ty":"gr","bm":0,"hd":false,"mn":"ADBE Vector Group","nm":"Group 11","ix":11,"cix":2,"np":2,"it":[{"ty":"sh","bm":0,"hd":false,"mn":"ADBE Vector Shape - Group","nm":"Path 1","ix":1,"d":1,"ks":{"a":0,"k":{"c":true,"i":[[-0.059,0.102],[0,0]],"o":[[0,0],[0.043,0.118]],"v":[[0.076,-0.059],[-0.076,-0.059]]},"ix":2}},{"ty":"fl","bm":0,"hd":false,"mn":"ADBE Vector Graphic - Fill","nm":"Fill 1","c":{"a":0,"k":[0.302,0.698,0.9059],"ix":4},"r":1,"o":{"a":0,"k":100,"ix":5}},{"ty":"tr","a":{"a":0,"k":[0,0],"ix":1},"s":{"a":0,"k":[100,100],"ix":3},"sk":{"a":0,"k":0,"ix":4},"p":{"a":0,"k":[588.373,199.13],"ix":2},"r":{"a":0,"k":0,"ix":6},"sa":{"a":0,"k":0,"ix":5},"o":{"a":0,"k":100,"ix":7}}]},{"ty":"gr","bm":0,"hd":false,"mn":"ADBE Vector Group","nm":"Group 12","ix":12,"cix":2,"np":2,"it":[{"ty":"sh","bm":0,"hd":false,"mn":"ADBE Vector Shape - Group","nm":"Path 1","ix":1,"d":1,"ks":{"a":0,"k":{"c":true,"i":[[-3.967,-6.455],[0,0],[0,0],[-6.142,4.407],[0,0]],"o":[[0,0],[0,0],[3.967,-6.455],[0,0],[6.141,4.407]],"v":[[-114.757,8.235],[-30.263,8.235],[114.753,8.235],[130.084,-8.235],[-130.084,-8.235]]},"ix":2}},{"ty":"fl","bm":0,"hd":false,"mn":"ADBE Vector Graphic - Fill","nm":"Fill 1","c":{"a":0,"k":[0.1098,0.6588,0.9412],"ix":4},"r":1,"o":{"a":0,"k":100,"ix":5}},{"ty":"tr","a":{"a":0,"k":[0,0],"ix":1},"s":{"a":0,"k":[100,100],"ix":3},"sk":{"a":0,"k":0,"ix":4},"p":{"a":0,"k":[309.645,239.897],"ix":2},"r":{"a":0,"k":0,"ix":6},"sa":{"a":0,"k":0,"ix":5},"o":{"a":0,"k":100,"ix":7}}]},{"ty":"gr","bm":0,"hd":false,"mn":"ADBE Vector Group","nm":"Group 13","ix":13,"cix":2,"np":2,"it":[{"ty":"sh","bm":0,"hd":false,"mn":"ADBE Vector Shape - Group","nm":"Path 1","ix":1,"d":1,"ks":{"a":0,"k":{"c":true,"i":[[-0.921,-8.771],[0,0],[-4.425,7.155],[0,0]],"o":[[0,0],[0.891,-8.771],[0,0],[4.424,7.155]],"v":[[-106.533,12.061],[106.563,12.061],[114.755,-12.061],[-114.755,-12.061]]},"ix":2}},{"ty":"fl","bm":0,"hd":false,"mn":"ADBE Vector Graphic - Fill","nm":"Fill 1","c":{"a":0,"k":[0.2314,0.5098,0.9647],"ix":4},"r":1,"o":{"a":0,"k":100,"ix":5}},{"ty":"tr","a":{"a":0,"k":[0,0],"ix":1},"s":{"a":0,"k":[100,100],"ix":3},"sk":{"a":0,"k":0,"ix":4},"p":{"a":0,"k":[309.643,260.193],"ix":2},"r":{"a":0,"k":0,"ix":6},"sa":{"a":0,"k":0,"ix":5},"o":{"a":0,"k":100,"ix":7}}]},{"ty":"gr","bm":0,"hd":false,"mn":"ADBE Vector Group","nm":"Group 14","ix":14,"cix":2,"np":2,"it":[{"ty":"sh","bm":0,"hd":false,"mn":"ADBE Vector Shape - Group","nm":"Path 1","ix":1,"d":1,"ks":{"a":0,"k":{"c":true,"i":[[0,0],[0,0],[0,0],[-4.424,7.155],[0,0]],"o":[[0,0],[0,0],[0.921,-8.772],[0,0],[0,0]],"v":[[-28.337,-3.029],[-28.337,12.061],[20.115,12.061],[28.337,-12.062],[-28.337,-12.062]]},"ix":2}},{"ty":"fl","bm":0,"hd":false,"mn":"ADBE Vector Graphic - Fill","nm":"Fill 1","c":{"a":0,"k":[0.2314,0.5098,0.9647],"ix":4},"r":1,"o":{"a":0,"k":100,"ix":5}},{"ty":"tr","a":{"a":0,"k":[0,0],"ix":1},"s":{"a":0,"k":[100,100],"ix":3},"sk":{"a":0,"k":0,"ix":4},"p":{"a":0,"k":[68.829,260.194],"ix":2},"r":{"a":0,"k":0,"ix":6},"sa":{"a":0,"k":0,"ix":5},"o":{"a":0,"k":100,"ix":7}}]},{"ty":"gr","bm":0,"hd":false,"mn":"ADBE Vector Group","nm":"Group 15","ix":15,"cix":2,"np":2,"it":[{"ty":"sh","bm":0,"hd":false,"mn":"ADBE Vector Shape - Group","nm":"Path 1","ix":1,"d":1,"ks":{"a":0,"k":{"c":true,"i":[[0,0],[0,0],[-6.141,4.407],[0,0]],"o":[[0,0],[3.963,-6.455],[0,0],[0,0]],"v":[[-36,8.235],[20.673,8.235],[36,-8.235],[-36,-8.235]]},"ix":2}},{"ty":"fl","bm":0,"hd":false,"mn":"ADBE Vector Graphic - Fill","nm":"Fill 1","c":{"a":0,"k":[0.1098,0.6588,0.9412],"ix":4},"r":1,"o":{"a":0,"k":100,"ix":5}},{"ty":"tr","a":{"a":0,"k":[0,0],"ix":1},"s":{"a":0,"k":[100,100],"ix":3},"sk":{"a":0,"k":0,"ix":4},"p":{"a":0,"k":[76.492,239.897],"ix":2},"r":{"a":0,"k":0,"ix":6},"sa":{"a":0,"k":0,"ix":5},"o":{"a":0,"k":100,"ix":7}}]}],"ind":8},{"ty":4,"nm":"Layer 7 Outlines","sr":1,"st":0,"op":301.000012259981,"ip":0,"hd":false,"ddd":0,"bm":0,"hasMask":false,"ao":0,"ks":{"a":{"a":0,"k":[47.958,47.956,0],"ix":1},"s":{"a":0,"k":[100,100,100],"ix":6},"sk":{"a":0,"k":0},"p":{"a":0,"k":[661.997,661.874,0],"ix":2},"r":{"a":1,"k":[{"o":{"x":0.167,"y":0.167},"i":{"x":0.833,"y":0.833},"s":[0],"t":0},{"s":[3600],"t":60.0000024438501}],"ix":10},"sa":{"a":0,"k":0},"o":{"a":0,"k":100,"ix":11}},"ef":[],"shapes":[{"ty":"gr","bm":0,"hd":false,"mn":"ADBE Vector Group","nm":"Group 1","ix":1,"cix":2,"np":2,"it":[{"ty":"sh","bm":0,"hd":false,"mn":"ADBE Vector Shape - Group","nm":"Path 1","ix":1,"d":1,"ks":{"a":0,"k":{"c":true,"i":[[16.579,0],[5.367,-5.431],[0,0],[0,8.29]],"o":[[-8.289,0],[0,0],[5.486,-5.422],[0,-16.638]],"v":[[-4.412,-25.643],[-25.643,-16.811],[16.818,25.643],[25.643,4.42]]},"ix":2}},{"ty":"fl","bm":0,"hd":false,"mn":"ADBE Vector Graphic - Fill","nm":"Fill 1","c":{"a":0,"k":[0.2314,0.5098,0.9647],"ix":4},"r":1,"o":{"a":0,"k":100,"ix":5}},{"ty":"tr","a":{"a":0,"k":[0,0],"ix":1},"s":{"a":0,"k":[100,100],"ix":3},"sk":{"a":0,"k":0,"ix":4},"p":{"a":0,"k":[52.369,43.562],"ix":2},"r":{"a":0,"k":0,"ix":6},"sa":{"a":0,"k":0,"ix":5},"o":{"a":0,"k":100,"ix":7}}]},{"ty":"gr","bm":0,"hd":false,"mn":"ADBE Vector Group","nm":"Group 2","ix":2,"cix":2,"np":2,"it":[{"ty":"sh","bm":0,"hd":false,"mn":"ADBE Vector Shape - Group","nm":"Path 1","ix":1,"d":1,"ks":{"a":0,"k":{"c":true,"i":[[0,-8.289],[-16.579,0],[-5.43,5.43],[0,0]],"o":[[0,16.58],[8.29,0],[0,0],[-5.485,5.481]],"v":[[-25.645,-4.413],[4.413,25.643],[25.645,16.812],[-16.818,-25.643]]},"ix":2}},{"ty":"fl","bm":0,"hd":false,"mn":"ADBE Vector Graphic - Fill","nm":"Fill 1","c":{"a":0,"k":[0.3804,0.5686,0.8667],"ix":4},"r":1,"o":{"a":0,"k":100,"ix":5}},{"ty":"tr","a":{"a":0,"k":[0,0],"ix":1},"s":{"a":0,"k":[100,100],"ix":3},"sk":{"a":0,"k":0,"ix":4},"p":{"a":0,"k":[43.543,52.394],"ix":2},"r":{"a":0,"k":0,"ix":6},"sa":{"a":0,"k":0,"ix":5},"o":{"a":0,"k":100,"ix":7}}]},{"ty":"gr","bm":0,"hd":false,"mn":"ADBE Vector Group","nm":"Group 3","ix":3,"cix":2,"np":4,"it":[{"ty":"sh","bm":0,"hd":false,"mn":"ADBE Vector Shape - Group","nm":"Path 1","ix":1,"d":1,"ks":{"a":0,"k":{"c":true,"i":[[5.485,-5.422],[8.29,0],[0,16.58],[-5.485,5.481],[-8.29,0],[0,-16.637]],"o":[[-5.43,5.431],[-16.579,0],[0,-8.289],[5.367,-5.431],[16.579,0],[0,8.29]],"v":[[21.231,21.248],[0,30.08],[-30.058,0.024],[-21.232,-21.205],[0,-30.036],[30.054,0.024]]},"ix":2}},{"ty":"sh","bm":0,"hd":false,"mn":"ADBE Vector Shape - Group","nm":"Path 2","ix":2,"d":1,"ks":{"a":0,"k":{"c":true,"i":[[1.467,2.698],[3.239,3.239],[13.174,0],[8.637,-8.637],[2.204,-4.06],[0.926,-2.985],[0,-4.94],[-26.348,0],[0,26.349],[1.396,4.484]],"o":[[-2.203,-4.06],[-8.633,-8.637],[-13.174,0],[-3.235,3.239],[-1.466,2.698],[-1.395,4.484],[0,26.349],[26.348,0],[0,-4.94],[-0.931,-2.985]],"v":[[41.951,-22.736],[33.734,-33.732],[0,-47.706],[-33.739,-33.732],[-41.951,-22.736],[-45.562,-14.186],[-47.708,0.001],[0,47.706],[47.708,0.001],[45.562,-14.186]]},"ix":2}},{"ty":"mm","bm":0,"hd":false,"mn":"ADBE Vector Filter - Merge","nm":"Merge Paths 1","mm":1},{"ty":"fl","bm":0,"hd":false,"mn":"ADBE Vector Graphic - Fill","nm":"Fill 1","c":{"a":0,"k":[0.2627,0.2667,0.2667],"ix":4},"r":1,"o":{"a":0,"k":100,"ix":5}},{"ty":"tr","a":{"a":0,"k":[0,0],"ix":1},"s":{"a":0,"k":[100,100],"ix":3},"sk":{"a":0,"k":0,"ix":4},"p":{"a":0,"k":[47.957,47.956],"ix":2},"r":{"a":0,"k":0,"ix":6},"sa":{"a":0,"k":0,"ix":5},"o":{"a":0,"k":100,"ix":7}}]}],"ind":9}],"v":"5.4.2","fr":29.9700012207031,"op":60.0000024438501,"ip":0,"assets":[]}